odoo10_addon_web_confirm_window_close-10.0.1.0.0-py2.7-nspkg.pth
odoo/addons/web_confirm_window_close/README.rst
odoo/addons/web_confirm_window_close/__init__.py
odoo/addons/web_confirm_window_close/__manifest__.py
odoo/addons/web_confirm_window_close/static/description/icon.png
odoo/addons/web_confirm_window_close/static/src/js/web_confirm_window_close.js
odoo/addons/web_confirm_window_close/views/assets.xml
odoo10_addon_web_confirm_window_close-10.0.1.0.0.dist-info/DESCRIPTION.rst
odoo10_addon_web_confirm_window_close-10.0.1.0.0.dist-info/METADATA
odoo10_addon_web_confirm_window_close-10.0.1.0.0.dist-info/RECORD
odoo10_addon_web_confirm_window_close-10.0.1.0.0.dist-info/WHEEL
odoo10_addon_web_confirm_window_close-10.0.1.0.0.dist-info/metadata.json
odoo10_addon_web_confirm_window_close-10.0.1.0.0.dist-info/namespace_packages.txt
odoo10_addon_web_confirm_window_close-10.0.1.0.0.dist-info/top_level.txt
